odoo/addons/mass_mailing_subscription_email/README.rst
odoo/addons/mass_mailing_subscription_email/__init__.py
odoo/addons/mass_mailing_subscription_email/__manifest__.py
odoo/addons/mass_mailing_subscription_email/hooks.py
odoo/addons/mass_mailing_subscription_email/controllers/__init__.py
odoo/addons/mass_mailing_subscription_email/controllers/main.py
odoo/addons/mass_mailing_subscription_email/data/mail_template.xml
odoo/addons/mass_mailing_subscription_email/i18n/mass_mailing_subscription_email.pot
odoo/addons/mass_mailing_subscription_email/i18n/pt.po
odoo/addons/mass_mailing_subscription_email/models/__init__.py
odoo/addons/mass_mailing_subscription_email/models/mail_mail.py
odoo/addons/mass_mailing_subscription_email/models/mailing_contact_subscription.py
odoo/addons/mass_mailing_subscription_email/models/mailing_list.py
odoo/addons/mass_mailing_subscription_email/readme/CONFIGURE.rst
odoo/addons/mass_mailing_subscription_email/readme/CONTRIBUTORS.rst
odoo/addons/mass_mailing_subscription_email/readme/DESCRIPTION.rst
odoo/addons/mass_mailing_subscription_email/static/description/icon.png
odoo/addons/mass_mailing_subscription_email/static/description/index.html
odoo/addons/mass_mailing_subscription_email/tests/__init__.py
odoo/addons/mass_mailing_subscription_email/tests/test_subscription_email.py
odoo/addons/mass_mailing_subscription_email/tests/test_unsubscribe_from_list.py
odoo/addons/mass_mailing_subscription_email/views/mailing_list.xml
odoo14_addon_mass_mailing_subscription_email-14.0.1.0.4.dist-info/METADATA
odoo14_addon_mass_mailing_subscription_email-14.0.1.0.4.dist-info/WHEEL
odoo14_addon_mass_mailing_subscription_email-14.0.1.0.4.dist-info/top_level.txt
odoo14_addon_mass_mailing_subscription_email-14.0.1.0.4.dist-info/RECORD
